apriorib1/__init__.py
apriorib1/__main__.py
apriorib1/apriorib1.py
apriorib1-1.0.2.dist-info/LICENSE.txt
apriorib1-1.0.2.dist-info/METADATA
apriorib1-1.0.2.dist-info/WHEEL
apriorib1-1.0.2.dist-info/top_level.txt
apriorib1-1.0.2.dist-info/RECORD
