Metadata-Version: 2.1
Name: apriorib1
Version: 1.0.2
Summary: A Python library that implements smooth and easy apriori for association rule mining. Currently limited for maximum 4 items/transaction.
Home-page: https://github.com/BALaka-18/apriorib1
Author: Balaka Biswas
Author-email: balaka2605@gmail.com
License: MIT
Platform: UNKNOWN
Classifier: License :: OSI Approved :: MIT License
Classifier: Programming Language :: Python :: 3.5
Classifier: Programming Language :: Python :: 3.6
Classifier: Programming Language :: Python :: 3.7
Classifier: Operating System :: OS Independent
Requires-Python: >=3.5
Requires-Dist: numpy
Requires-Dist: pandas
